[
    {
        "title" : "Home",
        "image" : "menu_home"
    },
    {
        "title" : "Holistic Lifestyle",
        "image" : "menu_lifestyle"
    },
    {
        "title" : "Holistic Clinic",
        "image" : "menu_clinic"
    },
    {
        "title" : "Holistic Hotels",
        "image" : "menu_hotel"
    },
    {
        "title" : "Holistic Restaurants",
        "image" : "menu_restaurant"
    },
    {
        "title" : "Holistic Products",
        "image" : "menu_product"
    },
    {
        "title" : "My Loyalty Points",
        "image" : "menu_point"
    },
    {
        "title" : "My Purchases",
        "image" : "menu_purchase"
    },
    {
        "title" : "Profile",
        "image" : "menu_profile"
    },
    {
        "title" : "Logout",
        "image" : "menu_logout"
    }
]
